<vdu-descriptor xmlns="urn:mitel:params:xml:vnf:yang:vdu">
<life-cycle-state-metadata>
		<metadata-id>DIAM_RE_LCMD_v5</metadata-id>
		<name>DIAM_RE_LCMD_v5</name>
		<communication>bi_directional_c</communication>
		<states>
			<state-name>InstantiatedNotConfigured</state-name>
			<state>
				<state-type>defaultState</state-type>
				<state-function>
					<package-name>com.mitel.epbroker.VNFLCMCommunicator</package-name>
					<function-list>
						<function-name>initializeVNFPOST</function-name>
						<function-argument>{&amp;quot;netconfPort&amp;quot;:&amp;quot;2022&amp;quot;,&amp;quot;resourceLocation&amp;quot;:&amp;quot;api/running/sys/platform&amp;quot; }</function-argument>
					</function-list>
				</state-function>
			</state>
			<lib-path>/opt/apache-tomcat-8.0.33/epbLIB/Mavenir_mOne_EPBroker.jar</lib-path>
			<event-list>
				<event-name>NotConfigure</event-name>
				<event-type>VM_NOTIFY_TRIGGER_EVT</event-type>
				<event>
					<next-success-state>InstantiatedNotConfigured</next-success-state>
					<next-failure-state>InstantiatedNotConfigured</next-failure-state>
					<actions>
						<package-name>com.mitel.epbroker.VNFLCMCommunicator</package-name>
						<function-list>
							<function-name>sendNotificationToCMS</function-name>
							<function-argument></function-argument>
						</function-list>
						<vdu-depends-on>[{&amp;quot;vnfdId&amp;quot;:&amp;quot;UAG_SC_VNFD1&amp;quot;,&amp;quot;vnfdVersion&amp;quot;:&amp;quot;UAG_VNFD_v5&amp;quot;,&amp;quot;vduId&amp;quot;:&amp;quot;UAG_SC&amp;quot;},{&amp;quot;vnfdId&amp;quot;:&amp;quot;FE_VNFD_A&amp;quot;,&amp;quot;vnfdVersion&amp;quot;:&amp;quot;UAG_VNFD_v5&amp;quot;,&amp;quot;vduId&amp;quot;:&amp;quot;UAG_VLB_FE1&amp;quot;},{&amp;quot;vnfdId&amp;quot;:&amp;quot;FE_VNFD_B&amp;quot;,&amp;quot;vnfdVersion&amp;quot;:&amp;quot;UAG_VNFD_v5&amp;quot;,&amp;quot;vduId&amp;quot;:&amp;quot;UAG_VLB_FE2&amp;quot;},{&amp;quot;vnfdId&amp;quot;:&amp;quot;FE_VNFD_B&amp;quot;,&amp;quot;vnfdVersion&amp;quot;:&amp;quot;UAG_VNFD_v5&amp;quot;,&amp;quot;vduId&amp;quot;:&amp;quot;UAG_VLB_FE1&amp;quot;}]</vdu-depends-on>
					</actions>
				</event>
			</event-list>
			<event-list>
				<event-name>InitSuccess</event-name>
				<event-type>VM_NOTIFY_TRIGGER_EVT</event-type>
				<event>
					<next-success-state>InstantiatedConfiguring</next-success-state>
					<next-failure-state>InstantiatedConfiguring</next-failure-state>
					<actions>
						<package-name>com.mitel.epbroker.PeerVNFLCMCommunicator</package-name>
						<function-list>
							<function-name>sendNotificationToCMS</function-name>
							<function-argument></function-argument>
						</function-list>
						<function-list>
							<function-name>updatePeerInfoPost</function-name>
							<function-argument>{&amp;quot;method&amp;quot;:&amp;quot;graceful&amp;quot;,&amp;quot;status&amp;quot;:&amp;quot;VNF_STATUS_INSTANTIATING&amp;quot;,&amp;quot;resourceLocation&amp;quot;:&amp;quot;api/running/sys/platform&amp;quot; }</function-argument>
						</function-list>
						<vdu-depends-on>[{&amp;quot;vnfdId&amp;quot;:&amp;quot;UAG_SC_VNFD1&amp;quot;,&amp;quot;vnfdVersion&amp;quot;:&amp;quot;UAG_VNFD_v5&amp;quot;,&amp;quot;vduId&amp;quot;:&amp;quot;UAG_SC&amp;quot;},{&amp;quot;vnfdId&amp;quot;:&amp;quot;FE_VNFD_A&amp;quot;,&amp;quot;vnfdVersion&amp;quot;:&amp;quot;UAG_VNFD_v5&amp;quot;,&amp;quot;vduId&amp;quot;:&amp;quot;UAG_VLB_FE1&amp;quot;},{&amp;quot;vnfdId&amp;quot;:&amp;quot;FE_VNFD_B&amp;quot;,&amp;quot;vnfdVersion&amp;quot;:&amp;quot;UAG_VNFD_v5&amp;quot;,&amp;quot;vduId&amp;quot;:&amp;quot;UAG_VLB_FE2&amp;quot;},{&amp;quot;vnfdId&amp;quot;:&amp;quot;FE_VNFD_B&amp;quot;,&amp;quot;vnfdVersion&amp;quot;:&amp;quot;UAG_VNFD_v5&amp;quot;,&amp;quot;vduId&amp;quot;:&amp;quot;UAG_VLB_FE1&amp;quot;}]</vdu-depends-on>
					</actions>
				</event>
			</event-list>
			<event-list>
				<event-name>InitFailure</event-name>
				<event>
					<next-success-state>InstantiatedNotConfigured</next-success-state>
					<next-failure-state>InstantiatedNotConfigured</next-failure-state>
					<actions>
						<package-name>com.mitel.epbroker.VNFLCMCommunicator</package-name>
						<function-list>
							<function-name>sendNotificationToCMS</function-name>
							<function-argument></function-argument>
						</function-list>
					</actions>
				</event>
			</event-list>
			<event-list>
				<event-name>Terminate</event-name>
				<termination-event>true_c</termination-event>
				<event-type>TERMINATION_EVT</event-type>
				<event>
     <next-success-state>Terminating</next-success-state>
     <next-failure-state>InstantiatedConfiguring</next-failure-state>
					<actions>
						<package-name>com.mitel.epbroker.VNFLCMCommunicator</package-name>
						<function-list>
							<function-name>defaultFunctionTrue</function-name>
							<function-argument>{&amp;quot;method&amp;quot;:&amp;quot;forceful&amp;quot;,&amp;quot;resourceLocation&amp;quot;:&amp;quot;api/running/sys/platform/vnf&amp;quot; }</function-argument>
						</function-list>
					</actions>
				</event>
			</event-list>
		</states>
		<states>
			<state-name>InstantiatedConfiguring</state-name>
			<state>
				<state-type>normalTransient</state-type>
				<state-function>
					<package-name>com.mitel.epbroker.VNFLCMCommunicator</package-name>
					<function-list>
						<function-name>defaultFunctionTrue</function-name>
						<function-argument>{&amp;quot;netconfPort&amp;quot;:&amp;quot;2022&amp;quot;,&amp;quot;resourceLocation&amp;quot;:&amp;quot;api/running/sys/platform&amp;quot; }</function-argument>
					</function-list>
				</state-function>
			</state>
			<lib-path>/opt/apache-tomcat-8.0.33/epbLIB/Mavenir_mOne_EPBroker.jar</lib-path>
			<event-list>
				<event-name>ConfigureSuccess</event-name>
				<event-type>VNF_READY_EVT</event-type>
				<event>
					<next-success-state>InstantiatedConfiguredInactive</next-success-state>
					<next-failure-state>InstantiatedConfiguring</next-failure-state>
					<actions>
						<package-name>com.mitel.epbroker.VNFLCMCommunicator</package-name>
						<function-list>
							<function-name>sendNotificationToCMS</function-name>
							<function-argument></function-argument>
						</function-list>
						<function-list>
							<function-name>startVNFPOST</function-name>
							<function-argument>{&amp;quot;operation&amp;quot;:&amp;quot;start&amp;quot;,&amp;quot;resourceLocation&amp;quot;:&amp;quot;api/running/sysops/lcm/_operations/start&amp;quot; }</function-argument>
						</function-list>
					</actions>
				</event>
			</event-list>
			<event-list>
				<event-name>ConfigureFailure</event-name>
				<event>
					<next-success-state>InstantiatedConfiguring</next-success-state>
					<next-failure-state>InstantiatedConfiguring</next-failure-state>
					<actions>
						<package-name>com.mitel.epbroker.VNFLCMCommunicator</package-name>
						<function-list>
							<function-name>sendNotificationToCMS</function-name>
							<function-argument></function-argument>
						</function-list>
						<function-list>
							<function-name>defaultFunctionTrue</function-name>
							<function-argument>{&amp;quot;method&amp;quot;:&amp;quot;graceful&amp;quot;,&amp;quot;resourceLocation&amp;quot;:&amp;quot;api/running/sys/platform/vnf&amp;quot; }</function-argument>
						</function-list>
					</actions>
				</event>
			</event-list>
			<event-list>
				<event-name>Terminate</event-name>
				<termination-event>false_c</termination-event>
				<event>
					<next-success-state>Terminating</next-success-state>
					<next-failure-state>InstantiatedConfiguring</next-failure-state>
					<actions>
						<package-name>com.mitel.epbroker.VNFLCMCommunicator</package-name>
						<function-list>
							<function-name>terminateVNFDELETE</function-name>
							<function-argument>{&amp;quot;method&amp;quot;:&amp;quot;forceful&amp;quot;,&amp;quot;resourceLocation&amp;quot;:&amp;quot;api/running/sys/platform/vnf&amp;quot; }</function-argument>
						</function-list>
					</actions>
				</event>
			</event-list>
			<event-list>
				<event-name>Terminated</event-name>
				<event>
					<next-success-state>Terminated</next-success-state>
					<next-failure-state>Terminated</next-failure-state>
					<actions>
						<package-name>com.mitel.epbroker.VNFLCMCommunicator</package-name>
						<function-list>
							<function-name>defaultFunctionTrue</function-name>
							<function-argument>{&amp;quot;method&amp;quot;:&amp;quot;graceful&amp;quot;,&amp;quot;resourceLocation&amp;quot;:&amp;quot;api/running/sys/platform/vnf&amp;quot; }</function-argument>
						</function-list>
						<function-list>
							<function-name>sendNotificationToCMS</function-name>
							<function-argument></function-argument>
						</function-list>
					</actions>
				</event>
			</event-list>
			<event-list>
				<event-name>ScaleIn</event-name>
				<termination-event>true_c</termination-event>
				<event-type>TERMINATION_EVT</event-type>
				<event>
     <next-success-state>Terminating</next-success-state>
     <next-failure-state>InstantiatedConfiguring</next-failure-state>
					<actions>
						<package-name>com.mitel.epbroker.VNFLCMCommunicator</package-name>
						<function-list>
							<function-name>stopVNFPOST</function-name>
							<function-argument>{&amp;quot;method&amp;quot;:&amp;quot;graceful&amp;quot;,&amp;quot;resourceLocation&amp;quot;:&amp;quot;api/running/sysops/lcm/_operations/stop&amp;quot; }</function-argument>
						</function-list>
						<function-list>
							<function-name>terminateVNFDELETE</function-name>
							<function-argument>{&amp;quot;method&amp;quot;:&amp;quot;forceful&amp;quot;,&amp;quot;resourceLocation&amp;quot;:&amp;quot;api/running/sys/platform/vnf&amp;quot; }</function-argument>
						</function-list>
					</actions>
				</event>
			</event-list>
		</states>
		<states>
			<state-name>InstantiatedConfiguredInactive</state-name>
			<state>
				<state-type>normalTransient</state-type>
				<state-function>
					<package-name>com.mitel.epbroker.VNFLCMCommunicator</package-name>
					<function-list>
						<function-name>defaultFunctionTrue</function-name>
						<function-argument>{&amp;quot;netconfPort&amp;quot;:&amp;quot;2022&amp;quot;,&amp;quot;resourceLocation&amp;quot;:&amp;quot;api/running/sys/platform&amp;quot; }</function-argument>
					</function-list>
				</state-function>
			</state>
			<lib-path>/opt/apache-tomcat-8.0.33/epbLIB/Mavenir_mOne_EPBroker.jar</lib-path>
			<event-list>
				<event-name>Start</event-name>
				<event>
					<next-success-state>InstantiatedConfiguredActivating</next-success-state>
					<next-failure-state>InstantiatedConfiguredInactive</next-failure-state>
					<actions>
						<package-name>com.mitel.epbroker.VNFLCMCommunicator</package-name>
						<function-list>
							<function-name>startVNFPOST</function-name>
							<function-argument>{&amp;quot;operation&amp;quot;:&amp;quot;start&amp;quot;,&amp;quot;resourceLocation&amp;quot;:&amp;quot;api/running/sysops/lcm/_operations/start&amp;quot; }</function-argument>
						</function-list>
					</actions>
				</event>
			</event-list>
			<event-list>
				<event-name>InitSuccessSync</event-name>
				<event-type>VM_SYNC_TRIGGER_EVT</event-type>
				<event>
					<next-success-state>InstantiatedConfiguredInactive</next-success-state>
					<next-failure-state>InstantiatedConfiguredInactive</next-failure-state>
					<actions>
						<package-name>com.mitel.epbroker.PeerVNFLCMCommunicator</package-name>
						<function-list>
							<function-name>updatePeerInfoSyncPost</function-name>
							<function-argument>{&amp;quot;method&amp;quot;:&amp;quot;graceful&amp;quot;,&amp;quot;status&amp;quot;:&amp;quot;VNF_STATUS_INS&amp;quot;,&amp;quot;resourceLocation&amp;quot;:&amp;quot;api/running/sys/platform&amp;quot; }</function-argument>
						</function-list>
						
					</actions>
				</event>
			</event-list>
			<event-list>
				<event-name>StartSuccess</event-name>
				<event-type>VNF_READY_INITIATE_NOTIFY_EVT</event-type>
				<event>
					<next-success-state>InstantiatedConfiguredActive</next-success-state>
					<next-failure-state>InstantiatedConfiguredActive</next-failure-state>
					<actions>
						<package-name>com.mitel.epbroker.PeerVNFLCMCommunicator</package-name>
						<function-list>
							<function-name>sendNotificationToCMS</function-name>
							<function-argument></function-argument>
						</function-list>
						<function-list>
							<function-name>sendMonitoringParam</function-name>
							<function-argument>{&amp;quot;method&amp;quot;:&amp;quot;graceful&amp;quot;,&amp;quot;resourceLocation&amp;quot;:&amp;quot;api/running/sys/platform&amp;quot; }</function-argument>
						</function-list>
						<function-list>
							<function-name>updatePeerInfoPut</function-name>
							<function-argument>{&amp;quot;method&amp;quot;:&amp;quot;graceful&amp;quot;,&amp;quot;status&amp;quot;:&amp;quot;VNF_STATUS_INS&amp;quot;,&amp;quot;resourceLocation&amp;quot;:&amp;quot;api/running/sys/platform&amp;quot; }</function-argument>
						</function-list>
						<vdu-depends-on>[{&amp;quot;vnfdId&amp;quot;:&amp;quot;UAG_SC_VNFD1&amp;quot;,&amp;quot;vnfdVersion&amp;quot;:&amp;quot;UAG_VNFD_v5&amp;quot;,&amp;quot;vduId&amp;quot;:&amp;quot;UAG_SC&amp;quot;},{&amp;quot;vnfdId&amp;quot;:&amp;quot;FE_VNFD_A&amp;quot;,&amp;quot;vnfdVersion&amp;quot;:&amp;quot;UAG_VNFD_v5&amp;quot;,&amp;quot;vduId&amp;quot;:&amp;quot;UAG_VLB_FE1&amp;quot;},{&amp;quot;vnfdId&amp;quot;:&amp;quot;FE_VNFD_B&amp;quot;,&amp;quot;vnfdVersion&amp;quot;:&amp;quot;UAG_VNFD_v5&amp;quot;,&amp;quot;vduId&amp;quot;:&amp;quot;UAG_VLB_FE2&amp;quot;},{&amp;quot;vnfdId&amp;quot;:&amp;quot;FE_VNFD_B&amp;quot;,&amp;quot;vnfdVersion&amp;quot;:&amp;quot;UAG_VNFD_v5&amp;quot;,&amp;quot;vduId&amp;quot;:&amp;quot;UAG_VLB_FE1&amp;quot;}]</vdu-depends-on>
					</actions>
				</event>
			</event-list>
			<event-list>
				<event-name>Terminate</event-name>
				<termination-event>false_c</termination-event>
				<event>
					<next-success-state>Terminating</next-success-state>
					<next-failure-state>InstantiatedConfiguredInactive</next-failure-state>
					<actions>
						<package-name>com.mitel.epbroker.VNFLCMCommunicator</package-name>
						<function-list>
							<function-name>terminateVNFDELETE</function-name>
							<function-argument>{&amp;quot;method&amp;quot;:&amp;quot;graceful&amp;quot;,&amp;quot;resourceLocation&amp;quot;:&amp;quot;api/running/sys/platform/vnf&amp;quot; }</function-argument>
						</function-list>
					</actions>
				</event>
			</event-list>
			<event-list>
				<event-name>ScaleIn</event-name>
				<termination-event>true_c</termination-event>
				<event-type>TERMINATION_EVT</event-type>
				<event>
     <next-success-state>Terminating</next-success-state>
     <next-failure-state>InstantiatedConfiguring</next-failure-state>
					<actions>
						<package-name>com.mitel.epbroker.VNFLCMCommunicator</package-name>
						<function-list>
							<function-name>stopVNFPOST</function-name>
							<function-argument>{&amp;quot;method&amp;quot;:&amp;quot;graceful&amp;quot;,&amp;quot;resourceLocation&amp;quot;:&amp;quot;api/running/sysops/lcm/_operations/stop&amp;quot; }</function-argument>
						</function-list>
						<function-list>
							<function-name>terminateVNFDELETE</function-name>
							<function-argument>{&amp;quot;method&amp;quot;:&amp;quot;forceful&amp;quot;,&amp;quot;resourceLocation&amp;quot;:&amp;quot;api/running/sys/platform/vnf&amp;quot; }</function-argument>
						</function-list>
					</actions>
				</event>
			</event-list>
			<event-list>
				<event-name>Terminated</event-name>
				<event>
					<next-success-state>Terminated</next-success-state>
					<next-failure-state>Terminated</next-failure-state>
					<actions>
						<package-name>com.mitel.epbroker.VNFLCMCommunicator</package-name>
						<function-list>
							<function-name>sendNotificationToCMS</function-name>
							<function-argument></function-argument>
						</function-list>
						<function-list>
							<function-name>defaultFunctionTrue</function-name>
							<function-argument>{&amp;quot;method&amp;quot;:&amp;quot;graceful&amp;quot;,&amp;quot;resourceLocation&amp;quot;:&amp;quot;api/running/sys/platform/vnf&amp;quot; }</function-argument>
						</function-list>
					</actions>
				</event>
			</event-list>
		</states>
		<states>
			<state-name>InstantiatedConfiguredActivating</state-name>
			<state>
				<state-type>normalTransient</state-type>
				<state-function>
					<package-name>com.mitel.epbroker.VNFLCMCommunicator</package-name>
					<function-list>
						<function-name>defaultFunctionTrue</function-name>
						<function-argument>{&amp;quot;netconfPort&amp;quot;:&amp;quot;2022&amp;quot;,&amp;quot;resourceLocation&amp;quot;:&amp;quot;api/running/sys/platform&amp;quot; }</function-argument>
					</function-list>
				</state-function>
			</state>
			<lib-path>/opt/apache-tomcat-8.0.33/epbLIB/Mavenir_mOne_EPBroker.jar</lib-path>
			<event-list>
				<event-name>StartSuccess</event-name>
				<event-type>VNF_READY_INITIATE_NOTIFY_EVT</event-type>
				<event>
					<next-success-state>InstantiatedConfiguredActive</next-success-state>
					<next-failure-state>InstantiatedConfiguredActive</next-failure-state>
					<actions>
						<package-name>com.mitel.epbroker.PeerVNFLCMCommunicator</package-name>
						<function-list>
							<function-name>sendNotificationToCMS</function-name>
							<function-argument></function-argument>
						</function-list>
						<function-list>
							<function-name>sendMonitoringParam</function-name>
							<function-argument>{&amp;quot;method&amp;quot;:&amp;quot;graceful&amp;quot;,&amp;quot;resourceLocation&amp;quot;:&amp;quot;api/running/sys/platform&amp;quot; }</function-argument>
						</function-list>
						<function-list>
							<function-name>updatePeerInfoPut</function-name>
							<function-argument>{&amp;quot;method&amp;quot;:&amp;quot;graceful&amp;quot;,&amp;quot;status&amp;quot;:&amp;quot;VNF_STATUS_INS&amp;quot;,&amp;quot;resourceLocation&amp;quot;:&amp;quot;api/running/sys/platform&amp;quot; }</function-argument>
						</function-list>
						<vdu-depends-on>[{&amp;quot;vnfdId&amp;quot;:&amp;quot;UAG_SC_VNFD1&amp;quot;,&amp;quot;vnfdVersion&amp;quot;:&amp;quot;UAG_VNFD_v5&amp;quot;,&amp;quot;vduId&amp;quot;:&amp;quot;UAG_SC&amp;quot;},{&amp;quot;vnfdId&amp;quot;:&amp;quot;FE_VNFD_A&amp;quot;,&amp;quot;vnfdVersion&amp;quot;:&amp;quot;UAG_VNFD_v5&amp;quot;,&amp;quot;vduId&amp;quot;:&amp;quot;UAG_VLB_FE1&amp;quot;},{&amp;quot;vnfdId&amp;quot;:&amp;quot;FE_VNFD_B&amp;quot;,&amp;quot;vnfdVersion&amp;quot;:&amp;quot;UAG_VNFD_v5&amp;quot;,&amp;quot;vduId&amp;quot;:&amp;quot;UAG_VLB_FE2&amp;quot;},{&amp;quot;vnfdId&amp;quot;:&amp;quot;FE_VNFD_B&amp;quot;,&amp;quot;vnfdVersion&amp;quot;:&amp;quot;UAG_VNFD_v5&amp;quot;,&amp;quot;vduId&amp;quot;:&amp;quot;UAG_VLB_FE1&amp;quot;}]</vdu-depends-on>
					</actions>
				</event>
			</event-list>
			<event-list>
				<event-name>StartFailure</event-name>
				<event>
					<next-success-state>InstantiatedConfiguredInactive</next-success-state>
					<next-failure-state>InstantiatedConfiguredInactive</next-failure-state>
					<actions>
						<package-name>com.mitel.epbroker.VNFLCMCommunicator</package-name>
						<function-list>
							<function-name>sendNotificationToCMS</function-name>
							<function-argument></function-argument>
						</function-list>
						<function-list>
							<function-name>defaultFunctionTrue</function-name>
							<function-argument>{&amp;quot;method&amp;quot;:&amp;quot;graceful&amp;quot;,&amp;quot;resourceLocation&amp;quot;:&amp;quot;api/running/sys/platform/vnf&amp;quot; }</function-argument>
						</function-list>
					</actions>
				</event>
			</event-list>
			<event-list>
				<event-name>Terminate</event-name>
				<termination-event>false_c</termination-event>
				<event>
					<next-success-state>Terminating</next-success-state>
					<next-failure-state>InstantiatedConfiguredActivating</next-failure-state>
					<actions>
						<package-name>com.mitel.epbroker.VNFLCMCommunicator</package-name>
						<function-list>
							<function-name>terminateVNFDELETE</function-name>
							<function-argument>{&amp;quot;method&amp;quot;:&amp;quot;forceful&amp;quot;,&amp;quot;resourceLocation&amp;quot;:&amp;quot;api/running/sys/platform/vnf&amp;quot; }</function-argument>
						</function-list>
					</actions>
				</event>
			</event-list>
			<event-list>
				<event-name>Terminated</event-name>
				<event>
					<next-success-state>Terminated</next-success-state>
					<next-failure-state>Terminated</next-failure-state>
					<actions>
						<package-name>com.mitel.epbroker.VNFLCMCommunicator</package-name>
						<function-list>
							<function-name>sendNotificationToCMS</function-name>
							<function-argument></function-argument>
						</function-list>
						<function-list>
							<function-name>defaultFunctionTrue</function-name>
							<function-argument>{&amp;quot;method&amp;quot;:&amp;quot;graceful&amp;quot;,&amp;quot;resourceLocation&amp;quot;:&amp;quot;api/running/sys/platform/vnf&amp;quot; }</function-argument>
						</function-list>
					</actions>
				</event>
			</event-list>
			<event-list>
				<event-name>ScaleIn</event-name>
				<termination-event>true_c</termination-event>
				<event-type>TERMINATION_EVT</event-type>
				<event>
     <next-success-state>Terminating</next-success-state>
     <next-failure-state>InstantiatedConfiguring</next-failure-state>
					<actions>
						<package-name>com.mitel.epbroker.VNFLCMCommunicator</package-name>
						<function-list>
							<function-name>stopVNFPOST</function-name>
							<function-argument>{&amp;quot;method&amp;quot;:&amp;quot;graceful&amp;quot;,&amp;quot;resourceLocation&amp;quot;:&amp;quot;api/running/sysops/lcm/_operations/stop&amp;quot; }</function-argument>
						</function-list>
						<function-list>
							<function-name>terminateVNFDELETE</function-name>
							<function-argument>{&amp;quot;method&amp;quot;:&amp;quot;forceful&amp;quot;,&amp;quot;resourceLocation&amp;quot;:&amp;quot;api/running/sys/platform/vnf&amp;quot; }</function-argument>
						</function-list>
					</actions>
				</event>
			</event-list>
		</states>
		<states>
			<state-name>InstantiatedConfiguredActive</state-name>
			<state>
				<state-type>normalStable</state-type>
				<state-function>
					<package-name>com.mitel.epbroker.VNFLCMCommunicator</package-name>
					<function-list>
						<function-name>defaultFunctionTrue</function-name>
						<function-argument>{&amp;quot;netconfPort&amp;quot;:&amp;quot;2022&amp;quot;,&amp;quot;resourceLocation&amp;quot;:&amp;quot;api/running/sys/platform&amp;quot; }</function-argument>
					</function-list>
				</state-function>
			</state>
			<lib-path>/opt/apache-tomcat-8.0.33/epbLIB/Mavenir_mOne_EPBroker.jar</lib-path>
			<event-list>
				<event-name>PrepareSwitchover</event-name>
				<event-type>FIRST_HEARTBEAT_LOSS_EVT</event-type>
				<event>
					<next-success-state>InstantiatedConfiguredActive</next-success-state>
					<next-failure-state>InstantiatedConfiguredActive</next-failure-state>
					<actions>
						<package-name>com.mitel.epbroker.VNFLCMCommunicator</package-name>
						<function-list>
							<function-name>prepareVNFForSwitchover</function-name>
							<function-argument>{&amp;quot;method&amp;quot;:&amp;quot;graceful&amp;quot;,&amp;quot;resourceLocation&amp;quot;:&amp;quot;api/running/sysops/lcm/_operations/switchover-prepare&amp;quot; }</function-argument>
						</function-list>
					</actions>
				</event>
			</event-list>
			<event-list>
				<event-name>InitSuccessSync</event-name>
				<event-type>VM_SYNC_TRIGGER_EVT</event-type>
				<event>
					<next-success-state>InstantiatedConfiguredActive</next-success-state>
					<next-failure-state>InstantiatedConfiguredActive</next-failure-state>
					<actions>
						<package-name>com.mitel.epbroker.PeerVNFLCMCommunicator</package-name>
						<function-list>
							<function-name>updatePeerInfoSyncPost</function-name>
							<function-argument>{&amp;quot;method&amp;quot;:&amp;quot;graceful&amp;quot;,&amp;quot;status&amp;quot;:&amp;quot;VNF_STATUS_INS&amp;quot;,&amp;quot;resourceLocation&amp;quot;:&amp;quot;api/running/sys/platform&amp;quot; }</function-argument>
						</function-list>
						
					</actions>
				</event>
			</event-list>
			<event-list>
				<event-name>CancelSwitchover</event-name>
				<termination-event>false_c</termination-event>
				<event-type>SUBSEQUENT_HB_RCVD_EVT</event-type>
				<event>
					<next-success-state>InstantiatedConfiguredActive</next-success-state>
					<next-failure-state>InstantiatedConfiguredActive</next-failure-state>
					<actions>
						<package-name>com.mitel.epbroker.VNFLCMCommunicator</package-name>
						<function-list>
							<function-name>cancelVNFSwitchover</function-name>
							<function-argument>{&amp;quot;method&amp;quot;:&amp;quot;graceful&amp;quot;,&amp;quot;resourceLocation&amp;quot;:&amp;quot;api/running/sysops/lcm/_operations/switchover-cancel&amp;quot; }</function-argument>
						</function-list>
					</actions>
				</event>
			</event-list>
			<event-list>
				<event-name>Switchover</event-name>
				<termination-event>false_c</termination-event>
				<event-type>VM_SWITCHOVER_EVT</event-type>
				<event>
					<next-success-state>InstantiatedConfiguredActive</next-success-state>
					<next-failure-state>InstantiatedConfiguredActive</next-failure-state>
					<actions>
						<package-name>com.mitel.epbroker.VNFLCMCommunicator</package-name>
						<function-list>
							<function-name>vnfSwitchover</function-name>
							<function-argument>{&amp;quot;method&amp;quot;:&amp;quot;graceful&amp;quot;,&amp;quot;resourceLocation&amp;quot;:&amp;quot;api/running/sysops/lcm/_operations/switchover&amp;quot;,&amp;quot;resourceLocation2&amp;quot;:&amp;quot;api/running/sys/platform&amp;quot; }</function-argument>
						</function-list>
					</actions>
				</event>
			</event-list>
			<event-list>
				<event-name>GracefulStop</event-name>
				<event>
					<next-success-state>InstantiatedConfiguredDeactivating</next-success-state>
					<next-failure-state>InstantiatedConfiguredActive</next-failure-state>
					<actions>
						<package-name>com.mitel.epbroker.VNFLCMCommunicator</package-name>
						<function-list>
							<function-name>stopVNFPOST</function-name>
							<function-argument>{&amp;quot;method&amp;quot;:&amp;quot;graceful&amp;quot;,&amp;quot;resourceLocation&amp;quot;:&amp;quot;api/running/sysops/lcm/_operations/stop&amp;quot; }</function-argument>
						</function-list>
					</actions>
				</event>
			</event-list>
			<event-list>
				<event-name>ForcefulStop</event-name>
				<event>
					<next-success-state>InstantiatedConfiguredDeactivating</next-success-state>
					<next-failure-state>InstantiatedConfiguredActive</next-failure-state>
					<actions>
						<package-name>com.mitel.epbroker.VNFLCMCommunicator</package-name>
						<function-list>
							<function-name>stopVNFPOST</function-name>
							<function-argument>{&amp;quot;method&amp;quot;:&amp;quot;forceful&amp;quot;,&amp;quot;resourceLocation&amp;quot;:&amp;quot;api/running/sysops/lcm/_operations/stop&amp;quot; }</function-argument>
						</function-list>
					</actions>
				</event>
			</event-list>
			<event-list>
				<event-name>Terminate</event-name>
				<termination-event>false_c</termination-event>
				<event>
					<next-success-state>Terminating</next-success-state>
					<next-failure-state>InstantiatedConfiguredActive</next-failure-state>
					<actions>
						<package-name>com.mitel.epbroker.VNFLCMCommunicator</package-name>
						<function-list>
							<function-name>terminateVNFDELETE</function-name>
							<function-argument>{&amp;quot;method&amp;quot;:&amp;quot;forceful&amp;quot;,&amp;quot;resourceLocation&amp;quot;:&amp;quot;api/running/sys/platform/vnf&amp;quot; }</function-argument>
						</function-list>
					</actions>
				</event>
			</event-list>
			<event-list>
				<event-name>Terminated</event-name>
				<event>
					<next-success-state>Terminated</next-success-state>
					<next-failure-state>Terminated</next-failure-state>
					<actions>
						<package-name>com.mitel.epbroker.VNFLCMCommunicator</package-name>
						<function-list>
							<function-name>sendNotificationToCMS</function-name>
							<function-argument></function-argument>
						</function-list>
						<function-list>
							<function-name>defaultFunctionTrue</function-name>
							<function-argument>{&amp;quot;method&amp;quot;:&amp;quot;graceful&amp;quot;,&amp;quot;resourceLocation&amp;quot;:&amp;quot;api/running/sys/platform/vnf&amp;quot; }</function-argument>
						</function-list>
					</actions>
				</event>
			</event-list>
			<event-list>
				<event-name>ScaleIn</event-name>
				<termination-event>true_c</termination-event>
				<event-type>TERMINATION_EVT</event-type>
				<event>
     <next-success-state>Terminating</next-success-state>
     <next-failure-state>InstantiatedConfiguring</next-failure-state>
					<actions>
						<package-name>com.mitel.epbroker.PeerVNFLCMCommunicator</package-name>
						<function-list>
							<function-name>stopVNFPOSTDependsOnVDU</function-name>
							<function-argument>{&amp;quot;method&amp;quot;:&amp;quot;graceful&amp;quot;,&amp;quot;resourceLocation&amp;quot;:&amp;quot;api/running/sysops/lcm/_operations/stop&amp;quot; }</function-argument>
						</function-list>
						<function-list>
							<function-name>updatePeerInfoDelete</function-name>
							<function-argument>{&amp;quot;method&amp;quot;:&amp;quot;forceful&amp;quot;,&amp;quot;resourceLocation&amp;quot;:&amp;quot;api/running/sys/platform&amp;quot; }</function-argument>
						</function-list>
						<vdu-depends-on>[{&amp;quot;vnfdId&amp;quot;:&amp;quot;UAG_SC_VNFD1&amp;quot;,&amp;quot;vnfdVersion&amp;quot;:&amp;quot;UAG_VNFD_v5&amp;quot;,&amp;quot;vduId&amp;quot;:&amp;quot;UAG_SC&amp;quot;},{&amp;quot;vnfdId&amp;quot;:&amp;quot;FE_VNFD_A&amp;quot;,&amp;quot;vnfdVersion&amp;quot;:&amp;quot;UAG_VNFD_v5&amp;quot;,&amp;quot;vduId&amp;quot;:&amp;quot;UAG_VLB_FE1&amp;quot;},{&amp;quot;vnfdId&amp;quot;:&amp;quot;FE_VNFD_B&amp;quot;,&amp;quot;vnfdVersion&amp;quot;:&amp;quot;UAG_VNFD_v5&amp;quot;,&amp;quot;vduId&amp;quot;:&amp;quot;UAG_VLB_FE2&amp;quot;},{&amp;quot;vnfdId&amp;quot;:&amp;quot;FE_VNFD_B&amp;quot;,&amp;quot;vnfdVersion&amp;quot;:&amp;quot;UAG_VNFD_v5&amp;quot;,&amp;quot;vduId&amp;quot;:&amp;quot;UAG_VLB_FE1&amp;quot;}]</vdu-depends-on>
					</actions>
				</event>
			</event-list>
			<event-list>
				<event-name>StopSuccess</event-name>
				<event>
					<next-success-state>InstantiatedConfiguredInactive</next-success-state>
					<next-failure-state>InstantiatedConfiguredInactive</next-failure-state>
					<actions>
						<package-name>com.mitel.epbroker.PeerVNFLCMCommunicator</package-name>
						<function-list>
							<function-name>sendNotificationToCMS</function-name>
							<function-argument></function-argument>
						</function-list>
						<function-list>
							<function-name>updatePeerInfoPut</function-name>
							<function-argument>{&amp;quot;method&amp;quot;:&amp;quot;graceful&amp;quot;,&amp;quot;status&amp;quot;:&amp;quot;VNF_STATUS_OOS&amp;quot;,&amp;quot;resourceLocation&amp;quot;:&amp;quot;api/running/sys/platform&amp;quot; }</function-argument>
						</function-list>
						<vdu-depends-on>[{&amp;quot;vnfdId&amp;quot;:&amp;quot;UAG_SC_VNFD1&amp;quot;,&amp;quot;vnfdVersion&amp;quot;:&amp;quot;UAG_VNFD_v5&amp;quot;,&amp;quot;vduId&amp;quot;:&amp;quot;UAG_SC&amp;quot;},{&amp;quot;vnfdId&amp;quot;:&amp;quot;FE_VNFD_A&amp;quot;,&amp;quot;vnfdVersion&amp;quot;:&amp;quot;UAG_VNFD_v5&amp;quot;,&amp;quot;vduId&amp;quot;:&amp;quot;UAG_VLB_FE1&amp;quot;},{&amp;quot;vnfdId&amp;quot;:&amp;quot;FE_VNFD_B&amp;quot;,&amp;quot;vnfdVersion&amp;quot;:&amp;quot;UAG_VNFD_v5&amp;quot;,&amp;quot;vduId&amp;quot;:&amp;quot;UAG_VLB_FE2&amp;quot;},{&amp;quot;vnfdId&amp;quot;:&amp;quot;FE_VNFD_B&amp;quot;,&amp;quot;vnfdVersion&amp;quot;:&amp;quot;UAG_VNFD_v5&amp;quot;,&amp;quot;vduId&amp;quot;:&amp;quot;UAG_VLB_FE1&amp;quot;}]</vdu-depends-on>
					</actions>
				</event>
			</event-list>
			<event-list>
				<event-name>InitSuccess</event-name>
				<event>
					<next-success-state>InstantiatedConfiguring</next-success-state>
					<next-failure-state>InstantiatedConfiguring</next-failure-state>
					<actions>
						<package-name>com.mitel.epbroker.VNFLCMCommunicator</package-name>
						<function-list>
							<function-name>defaultFunctionTrue</function-name>
							<function-argument>{&amp;quot;method&amp;quot;:&amp;quot;graceful&amp;quot;,&amp;quot;resourceLocation&amp;quot;:&amp;quot;api/running/sys/platform&amp;quot; }</function-argument>
						</function-list>
					</actions>
				</event>
			</event-list>
		</states>
		<states>
			<state-name>InstantiatedConfiguredDeactivating</state-name>
			<state>
				<state-type>normalTransient</state-type>
				<state-function>
					<package-name>com.mitel.epbroker.VNFLCMCommunicator</package-name>
					<function-list>
						<function-name>defaultFunctionTrue</function-name>
						<function-argument>{&amp;quot;netconfPort&amp;quot;:&amp;quot;2022&amp;quot;,&amp;quot;resourceLocation&amp;quot;:&amp;quot;api/running/sys/platform&amp;quot; }</function-argument>
					</function-list>
				</state-function>
			</state>
			<lib-path>/opt/apache-tomcat-8.0.33/epbLIB/Mavenir_mOne_EPBroker.jar</lib-path>
			<event-list>
				<event-name>StopSuccess</event-name>
				<event>
					<next-success-state>InstantiatedConfiguredInactive</next-success-state>
					<next-failure-state>InstantiatedConfiguredInactive</next-failure-state>
					<actions>
						<package-name>com.mitel.epbroker.PeerVNFLCMCommunicator</package-name>
						<function-list>
							<function-name>sendNotificationToCMS</function-name>
							<function-argument></function-argument>
						</function-list>
						<function-list>
							<function-name>updatePeerInfoPut</function-name>
							<function-argument>{&amp;quot;method&amp;quot;:&amp;quot;graceful&amp;quot;,&amp;quot;status&amp;quot;:&amp;quot;VNF_STATUS_OOS&amp;quot;,&amp;quot;resourceLocation&amp;quot;:&amp;quot;api/running/sys/platform&amp;quot; }</function-argument>
						</function-list>
						<vdu-depends-on>[{&amp;quot;vnfdId&amp;quot;:&amp;quot;UAG_SC_VNFD1&amp;quot;,&amp;quot;vnfdVersion&amp;quot;:&amp;quot;UAG_VNFD_v5&amp;quot;,&amp;quot;vduId&amp;quot;:&amp;quot;UAG_SC&amp;quot;},{&amp;quot;vnfdId&amp;quot;:&amp;quot;FE_VNFD_A&amp;quot;,&amp;quot;vnfdVersion&amp;quot;:&amp;quot;UAG_VNFD_v5&amp;quot;,&amp;quot;vduId&amp;quot;:&amp;quot;UAG_VLB_FE1&amp;quot;},{&amp;quot;vnfdId&amp;quot;:&amp;quot;FE_VNFD_B&amp;quot;,&amp;quot;vnfdVersion&amp;quot;:&amp;quot;UAG_VNFD_v5&amp;quot;,&amp;quot;vduId&amp;quot;:&amp;quot;UAG_VLB_FE2&amp;quot;},{&amp;quot;vnfdId&amp;quot;:&amp;quot;FE_VNFD_B&amp;quot;,&amp;quot;vnfdVersion&amp;quot;:&amp;quot;UAG_VNFD_v5&amp;quot;,&amp;quot;vduId&amp;quot;:&amp;quot;UAG_VLB_FE1&amp;quot;}]</vdu-depends-on>
					</actions>
				</event>
			</event-list>
			<event-list>
				<event-name>StopFailure</event-name>
				<event>
					<next-success-state>InstantiatedConfiguredActive</next-success-state>
					<next-failure-state>InstantiatedConfiguredActive</next-failure-state>
					<actions>
						<package-name>com.mitel.epbroker.VNFLCMCommunicator</package-name>
						<function-list>
							<function-name>sendNotificationToCMS</function-name>
							<function-argument></function-argument>
						</function-list>
						<function-list>
							<function-name>defaultFunctionTrue</function-name>
							<function-argument>{&amp;quot;method&amp;quot;:&amp;quot;graceful&amp;quot;,&amp;quot;resourceLocation&amp;quot;:&amp;quot;api/running/sys/platform/vnf&amp;quot; }</function-argument>
						</function-list>
					</actions>
				</event>
			</event-list>
			<event-list>
				<event-name>Terminate</event-name>
				<termination-event>false_c</termination-event>
				<event>
					<next-success-state>Terminating</next-success-state>
					<next-failure-state>InstantiatedConfiguredDeactivating</next-failure-state>
					<actions>
						<package-name>com.mitel.epbroker.VNFLCMCommunicator</package-name>
						<function-list>
							<function-name>terminateVNFDELETE</function-name>
							<function-argument>{&amp;quot;method&amp;quot;:&amp;quot;forceful&amp;quot;,&amp;quot;resourceLocation&amp;quot;:&amp;quot;api/running/sys/platform/vnf&amp;quot; }</function-argument>
						</function-list>
					</actions>
				</event>
			</event-list>
			<event-list>
				<event-name>Terminated</event-name>
				<event>
					<next-success-state>Terminated</next-success-state>
					<next-failure-state>Terminated</next-failure-state>
					<actions>
						<package-name>com.mitel.epbroker.VNFLCMCommunicator</package-name>
						<function-list>
							<function-name>sendNotificationToCMS</function-name>
							<function-argument></function-argument>
						</function-list>
						<function-list>
							<function-name>defaultFunctionTrue</function-name>
							<function-argument>{&amp;quot;method&amp;quot;:&amp;quot;graceful&amp;quot;,&amp;quot;resourceLocation&amp;quot;:&amp;quot;api/running/sys/platform/vnf&amp;quot; }</function-argument>
						</function-list>
					</actions>
				</event>
			</event-list>
			<event-list>
				<event-name>ScaleIn</event-name>
				<termination-event>true_c</termination-event>
				<event-type>TERMINATION_EVT</event-type>
				<event>
     <next-success-state>Terminating</next-success-state>
     <next-failure-state>InstantiatedConfiguring</next-failure-state>
					<actions>
						<package-name>com.mitel.epbroker.VNFLCMCommunicator</package-name>
						<function-list>
							<function-name>stopVNFPOST</function-name>
							<function-argument>{&amp;quot;method&amp;quot;:&amp;quot;graceful&amp;quot;,&amp;quot;resourceLocation&amp;quot;:&amp;quot;api/running/sysops/lcm/_operations/stop&amp;quot; }</function-argument>
						</function-list>
						<function-list>
							<function-name>terminateVNFDELETE</function-name>
							<function-argument>{&amp;quot;method&amp;quot;:&amp;quot;forceful&amp;quot;,&amp;quot;resourceLocation&amp;quot;:&amp;quot;api/running/sys/platform/vnf&amp;quot; }</function-argument>
						</function-list>
					</actions>
				</event>
			</event-list>
		</states>
		<states>
			<state-name>Terminating</state-name>
			<state>
				<state-type>normalTransient</state-type>
				<state-function>
					<package-name>com.mitel.epbroker.VNFLCMCommunicator</package-name>
					<function-list>
						<function-name>defaultFunctionTrue</function-name>
						<function-argument>{&amp;quot;netconfPort&amp;quot;:&amp;quot;2022&amp;quot;,&amp;quot;resourceLocation&amp;quot;:&amp;quot;api/running/sys/platform&amp;quot; }</function-argument>
					</function-list>
				</state-function>
			</state>
			<lib-path>/opt/apache-tomcat-8.0.33/epbLIB/Mavenir_mOne_EPBroker.jar</lib-path>
			<event-list>
				<event-name>Terminated</event-name>
				<event>
					<next-success-state>Terminated</next-success-state>
					<next-failure-state>Terminated</next-failure-state>
					<actions>
						<package-name>com.mitel.epbroker.VNFLCMCommunicator</package-name>
						<function-list>
							<function-name>sendNotificationToCMS</function-name>
							<function-argument></function-argument>
						</function-list>
						<function-list>
							<function-name>defaultFunctionTrue</function-name>
							<function-argument>{&amp;quot;method&amp;quot;:&amp;quot;graceful&amp;quot;,&amp;quot;resourceLocation&amp;quot;:&amp;quot;api/running/sys/platform/vnf&amp;quot; }</function-argument>
						</function-list>
						<vdu-depends-on>[{&amp;quot;vnfdId&amp;quot;:&amp;quot;UAG_SC_VNFD1&amp;quot;,&amp;quot;vnfdVersion&amp;quot;:&amp;quot;UAG_VNFD_v5&amp;quot;,&amp;quot;vduId&amp;quot;:&amp;quot;UAG_SC&amp;quot;},{&amp;quot;vnfdId&amp;quot;:&amp;quot;FE_VNFD_A&amp;quot;,&amp;quot;vnfdVersion&amp;quot;:&amp;quot;UAG_VNFD_v5&amp;quot;,&amp;quot;vduId&amp;quot;:&amp;quot;UAG_VLB_FE1&amp;quot;},{&amp;quot;vnfdId&amp;quot;:&amp;quot;FE_VNFD_B&amp;quot;,&amp;quot;vnfdVersion&amp;quot;:&amp;quot;UAG_VNFD_v5&amp;quot;,&amp;quot;vduId&amp;quot;:&amp;quot;UAG_VLB_FE2&amp;quot;},{&amp;quot;vnfdId&amp;quot;:&amp;quot;FE_VNFD_B&amp;quot;,&amp;quot;vnfdVersion&amp;quot;:&amp;quot;UAG_VNFD_v5&amp;quot;,&amp;quot;vduId&amp;quot;:&amp;quot;UAG_VLB_FE1&amp;quot;}]</vdu-depends-on>
					</actions>
				</event>
			</event-list>
		</states>
		<states>
			<state-name>Terminated</state-name>
			<state>
				<state-type>endState</state-type>
				<state-function>
					<package-name>com.mitel.epbroker.VNFLCMCommunicator</package-name>
					<function-list>
						<function-name>defaultFunctionTrue</function-name>
						<function-argument>{&amp;quot;netconfPort&amp;quot;:&amp;quot;2022&amp;quot;,&amp;quot;resourceLocation&amp;quot;:&amp;quot;api/running/sys/platform&amp;quot; }</function-argument>
					</function-list>
				</state-function>
			</state>
			<lib-path>/opt/apache-tomcat-8.0.33/epbLIB/Mavenir_mOne_EPBroker.jar</lib-path>
		</states>
		<delay>30</delay>
</life-cycle-state-metadata>
</vdu-descriptor>
