<nsd xmlns="urn:mitel:params:xml:vnf:yang:nsd">
       <nsd-list>
              <id>NSD_UAGTDM01</id>
              <version>v716280</version>
              <name>NSD_UAGTDM01</name>
              <vendor>Mavenir</vendor>
              <description>NSD For UAG Solution</description>
              <connecting-device>
                     <id>router_3</id>
                     <type>router</type>
                     <name>router_3</name>
                     <router-creation-type>new_c</router-creation-type>
              </connecting-device>
              <monitoring-params>
                     <param-name>cpu_util</param-name>
                     <interface>Vi_vnfm_c</interface>
                     <enabled>started_c</enabled>
                     <measurement-type>periodic_c</measurement-type>
                     <periodicity>10</periodicity>
                 </monitoring-params>
              <vnf-ref-list>
                     <vnfd-id>VNFD_UAGTDM01GRE001</vnfd-id>
                     <version>v716280</version>
                 </vnf-ref-list>
              <vnf-ref-list>
                     <vnfd-id>VNFD_UAGTDM01UPC001</vnfd-id>
                     <version>v716280</version>
                 </vnf-ref-list>
              <vnf-ref-list>
                     <vnfd-id>VNFD_UAGTDM01DRE001</vnfd-id>
                     <version>v716280</version>
                 </vnf-ref-list>
              <vnf-ref-list>
                     <vnfd-id>VNFD_UAGTDM01APP001</vnfd-id>
                     <version>v716280</version>
                 </vnf-ref-list>
              <vnf-ref-list>
                     <vnfd-id>VNFD_UAGTDM04MPU001</vnfd-id>
                     <version>v716280</version>
                 </vnf-ref-list>
              <vnf-ref-list>
                     <vnfd-id>VNFD_UAGTDM04TRC001</vnfd-id>
                     <version>v716280</version>
                 </vnf-ref-list>
              <vnf-ref-list>
                     <vnfd-id>VNFD_UAGTDM01SRE001</vnfd-id>
                     <version>v716280</version>
                 </vnf-ref-list>
		      <vnf-ref-list>
			        <vnfd-id>VNFD_UAGTDM01VFE001</vnfd-id>
			        <version>v716280</version>
		      </vnf-ref-list>
              <connection-points>
                     <connection-point-id>UAG_CP_OAM</connection-point-id>
                     <idx>1</idx>
                     <description>UAG OAM network for VNFM/CMS</description>
                     <virtual-binding-type>router</virtual-binding-type>
                     <virtual-binding>router_3</virtual-binding>
                     <interface-binding>if1-1234-abcd-efgh-5678</interface-binding>
                     <virtual-link-id>Dummy</virtual-link-id>
                 </connection-points>
              <virtual-links>
                     <virtual-link-id>Dummy</virtual-link-id>
                     <version>v716280</version>
                     <idx>1</idx>
              </virtual-links>              
			  <virtual-links>
                     <virtual-link-id>NW-vIMS-VIM1-OAM_Internal</virtual-link-id>
                     <version>v716280</version>
                     <idx>2</idx>
              </virtual-links>
			  <virtual-links>
                     <virtual-link-id>NW-vIMS-VIM1-OAM_External</virtual-link-id>
                     <version>v716280</version>
                     <idx>3</idx>
               </virtual-links>
              <virtual-links>
                     <virtual-link-id>NW-vIMS-VIM1_H248</virtual-link-id>
                     <version>v716280</version>
                     <idx>4</idx>
                 </virtual-links>
              <virtual-links>
                     <virtual-link-id>NW-vIMS-VIM1-Session_DB</virtual-link-id>
                     <version>v716280</version>
                     <idx>5</idx>
                 </virtual-links>
              <virtual-links>
                     <virtual-link-id>NW-vIMS-VIM1_Core_Diameter</virtual-link-id>
                     <version>v716280</version>
                     <idx>6</idx>
                 </virtual-links>
              <virtual-links>
                     <virtual-link-id>NW-vIMS-VIM1-GRE_Tunnel</virtual-link-id>
                     <version>v716280</version>
                     <idx>7</idx>
                 </virtual-links>
              <virtual-links>
                     <virtual-link-id>NW-vIMS-VIM1-GM_Access_ipv6</virtual-link-id>
                     <version>v716280</version>
                     <idx>8</idx>
                 </virtual-links>
              <virtual-links>
                     <virtual-link-id>NW-vIMS-VIM1_Core_Signalling</virtual-link-id>
                     <version>v716280</version>
                     <idx>9</idx>
                 </virtual-links>
              <virtual-links>
                     <virtual-link-id>NW-vIMS-VIM1-EMX_Signalling</virtual-link-id>
                     <version>v716280</version>
                     <idx>10</idx>
                 </virtual-links>
                 <virtual-links>
                     <virtual-link-id>NW-vIMS-VIM1-GM_Access_ipv4</virtual-link-id>
                     <version>v716280</version>
                     <idx>11</idx>
                 </virtual-links>
                 <virtual-links>
                     <virtual-link-id>NW-vIMS-VIM1-CAS_Internal</virtual-link-id>
                     <version>v716280</version>
                     <idx>12</idx>
                 </virtual-links>
                 <virtual-links>
                     <virtual-link-id>NW-vIMS-VIM1_LI</virtual-link-id>
                     <version>v716280</version>
                     <idx>13</idx>
                 </virtual-links>
                 <virtual-links>
                     <virtual-link-id>NW-vIMS-VIM1_LI_x3</virtual-link-id>
                     <version>v716280</version>
                     <idx>14</idx>
                 </virtual-links>
                 <virtual-links>
                     <virtual-link-id>NW-vIMS-VIM1_FE_Charging</virtual-link-id>
                     <version>v716280</version>
                     <idx>15</idx>
                 </virtual-links>
                 <virtual-links>
                     <virtual-link-id>NW-vIMS-VIM1-Core_Media</virtual-link-id>
                     <version>v716280</version>
                     <idx>16</idx>
                 </virtual-links>
                 <virtual-links>
                     <virtual-link-id>NW-vIMS-VIM1_RTP</virtual-link-id>
                     <version>v716280</version>
                     <idx>17</idx>
                 </virtual-links>
                 <virtual-links>
                     <virtual-link-id>NW-vIMS-VIM1_I2_Signalling</virtual-link-id>
                     <version>v716280</version>
                     <idx>18</idx>
                 </virtual-links>                 
              <service-deployment-flavour>
                     <flavor-id>flv1</flavor-id>
                     <flavor-id-index>3</flavor-id-index>
					    <constituent-vnf>
                            <constituent-vnf-idx>1</constituent-vnf-idx>
                            <vnfd-id>VNFD_UAGTDM01GRE001</vnfd-id>
                            <server-group-name>8560b35c-1392-4252-8f31-63f8c2fe7066</server-group-name>
                            <vnf-mode>active_c</vnf-mode>
                        </constituent-vnf>
                     <constituent-vnf>
                            <constituent-vnf-idx>2</constituent-vnf-idx>
                            <vnfd-id>VNFD_UAGTDM01UPC001</vnfd-id>
                            <server-group-name>bbe0888e-c46c-4602-bff1-1a327b7837cc</server-group-name>
                            <vnf-mode>active_c</vnf-mode>
                        </constituent-vnf>
                     <constituent-vnf>
                            <constituent-vnf-idx>3</constituent-vnf-idx>
                            <vnfd-id>VNFD_UAGTDM01DRE001</vnfd-id>
                            <server-group-name>0ec24c9d-38ec-4daa-9f78-08e3e745dd69</server-group-name>
                            <vnf-mode>active_c</vnf-mode>
                        </constituent-vnf>
                     <constituent-vnf>
                            <constituent-vnf-idx>4</constituent-vnf-idx>
                            <vnfd-id>VNFD_UAGTDM01APP001</vnfd-id>
                            <server-group-name>abf2ce80-e538-4c2d-bc6c-0fe6457d0ced</server-group-name>
                            <vnf-mode>active_c</vnf-mode>
                        </constituent-vnf>						
                     <constituent-vnf>
                            <constituent-vnf-idx>5</constituent-vnf-idx>
                            <vnfd-id>VNFD_UAGTDM04MPU001</vnfd-id>
                            <server-group-name>5c329e85-3e1c-48e1-884e-ad4cdd1f2746</server-group-name>
                            <vnf-mode>active_c</vnf-mode>
                        </constituent-vnf>
					 <constituent-vnf>
                            <constituent-vnf-idx>6</constituent-vnf-idx>
                            <vnfd-id>VNFD_UAGTDM04TRC001</vnfd-id>
                            <server-group-name>abf2ce80-e538-4c2d-bc6c-0fe6457d0ced</server-group-name>
                            <vnf-mode>active_c</vnf-mode>
                        </constituent-vnf>
                    <constituent-vnf>
                            <constituent-vnf-idx>7</constituent-vnf-idx>
                            <vnfd-id>VNFD_UAGTDM01SRE001</vnfd-id>
                            <server-group-name>35e30487-de8e-4528-a801-9f1f5f28d259</server-group-name>
                            <vnf-mode>active_c</vnf-mode>
                        </constituent-vnf>						
                     <constituent-vnf>
                            <constituent-vnf-idx>8</constituent-vnf-idx>
                            <vnfd-id>VNFD_UAGTDM01VFE001</vnfd-id>
                            <server-group-name>580fca96-611a-4078-a350-fff9936eddde</server-group-name>
                            <vnf-mode>active_c</vnf-mode>
                        </constituent-vnf>
                 </service-deployment-flavour>
              <custom-user-data></custom-user-data>
              <precondition></precondition>
          </nsd-list>
   </nsd>
